nodeflux/analytics/v1beta1/analytic_pb2.py
nodeflux/analytics/v1beta1/analytic_pb2_grpc.py
nodeflux/analytics/v1beta1/face_demography_pb2.py
nodeflux/analytics/v1beta1/face_demography_pb2_grpc.py
nodeflux/analytics/v1beta1/face_detection_pb2.py
nodeflux/analytics/v1beta1/face_detection_pb2_grpc.py
nodeflux/analytics/v1beta1/face_enrollment_pb2.py
nodeflux/analytics/v1beta1/face_enrollment_pb2_grpc.py
nodeflux/analytics/v1beta1/face_match_pb2.py
nodeflux/analytics/v1beta1/face_match_pb2_grpc.py
nodeflux/analytics/v1beta1/face_recognition_pb2.py
nodeflux/analytics/v1beta1/face_recognition_pb2_grpc.py
nodeflux/analytics/v1beta1/image_classification_pb2.py
nodeflux/analytics/v1beta1/image_classification_pb2_grpc.py
nodeflux/analytics/v1beta1/license_plate_recognition_pb2.py
nodeflux/analytics/v1beta1/license_plate_recognition_pb2_grpc.py
nodeflux/analytics/v1beta1/vehicle_detection_pb2.py
nodeflux/analytics/v1beta1/vehicle_detection_pb2_grpc.py
nodeflux/api/v1beta1/image_analytic_pb2.py
nodeflux/api/v1beta1/image_analytic_pb2_grpc.py
nodeflux/types/v1beta1/bounding_box_pb2.py
nodeflux/types/v1beta1/bounding_box_pb2_grpc.py
nodeflux/types/v1beta1/embedding_pb2.py
nodeflux/types/v1beta1/embedding_pb2_grpc.py
nodeflux/types/v1beta1/image_pb2.py
nodeflux/types/v1beta1/image_pb2_grpc.py
nodefluxapis-0.2.6.dist-info/LICENSE
nodefluxapis-0.2.6.dist-info/METADATA
nodefluxapis-0.2.6.dist-info/WHEEL
nodefluxapis-0.2.6.dist-info/top_level.txt
nodefluxapis-0.2.6.dist-info/RECORD
