Metadata-Version: 2.1
Name: nodefluxapis
Version: 0.2.6
Summary: Nodeflux APIs.
Home-page: https://gitlab.com/nodefluxio/nodefluxapis
Author: Ilham Imaduddin
Author-email: ilham@nodeflux.io
License: Apache License 2.0
Platform: UNKNOWN
Classifier: License :: OSI Approved :: Apache Software License
Classifier: Programming Language :: Python
Classifier: Programming Language :: Python :: 3
Classifier: Programming Language :: Python :: 3.4
Classifier: Programming Language :: Python :: 3.5
Classifier: Programming Language :: Python :: 3.6
Classifier: Programming Language :: Python :: 3.7
Requires-Python: >=3.4.0
Requires-Dist: protobuf
Requires-Dist: grpcio
Requires-Dist: googleapis-common-protos
